tkitSeg/__init__.py
tkitSeg/model_troch_export.onnx
tkitSeg/seg.py
tkitSeg/special_tokens_map.json
tkitSeg/tokenizer_config.json
tkitSeg/vocab.txt
tkitSeg-0.0.0.5.1.dist-info/LICENSE
tkitSeg-0.0.0.5.1.dist-info/METADATA
tkitSeg-0.0.0.5.1.dist-info/WHEEL
tkitSeg-0.0.0.5.1.dist-info/top_level.txt
tkitSeg-0.0.0.5.1.dist-info/RECORD
