Metadata-Version: 2.1
Name: tkitSeg
Version: 0.0.0.5.1
Summary: Terry toolkit tkitSeg,一个中文分词和词性标注工具
Home-page: https://docs.terrychan.org/tkit-seg/
Author: Terry Chan
Author-email: napoler2008@gmail.com
License: UNKNOWN
Platform: UNKNOWN
License-File: LICENSE
Requires-Dist: numpy (>=1.21.2)
Requires-Dist: onnx (>=1.10.1)
Requires-Dist: onnxruntime (>=1.9.0)
Requires-Dist: transformers (>=4.10.3)
